{
    "images": [
        "http://steamtec.vn/assets/imgs/6a08e4e4-0f2f-4128-9bd3-d3e5fda52140.jpg",
        "http://steamtec.vn/assets/imgs/0fed07c2-064f-4f09-88e0-823335b68181.jpg",
        "http://steamtec.vn/assets/imgs/cf3d2a52-5cb1-4fb7-81e9-433398206baa.jpg",
        "http://steamtec.vn/assets/imgs/30855d62-45d9-4571-9fd8-b48432ebccea.jpg",
        "http://steamtec.vn/assets/imgs/8137b7f1-4f28-4f11-8c2e-6d4f39673e81.jpg"
    ],
    "id": "447",
    "product": {
        "name": "BT-W295F",
        "code": "BT-W295F",
        "brand": "2160x1760x780mm"
    },
    "details": [
        {
            "name": "BT-W295F",
            "value": "QT"
        },
        {
            "name": "Control system",
            "value": "1pc"
        },
        {
            "name": "Water pump",
            "value": "2.2kWx1pc\n\n0.37kWx1pc"
        },
        {
            "name": "Heater",
            "value": "3kWx1pc"
        },
        {
            "name": "Filter",
            "value": "1pc"
        },
        {
            "name": "Ozone",
            "value": "1pc"
        },
        {
            "name": "LED light",
            "value": "LED:1pc"
        },
        {
            "name": "Jet",
            "value": "3.5\"jet:7pcs\n\n2.5\"jet:23pcs"
        },
        {
            "name": "Waterfall",
            "value": "1pc"
        },
        {
            "name": "Air adjuster",
            "value": "2pcs"
        },
        {
            "name": "Pillow",
            "value": "2pcs"
        },
        {
            "name": "Water drainer",
            "value": "1pc"
        },
        {
            "name": "FRP bottom",
            "value": "√"
        },
        {
            "name": "Cubage（m³）",
            "value": "1.6m³"
        },
        {
            "name": "Seat",
            "value": "5pcs"
        },
        {
            "name": "Total power",
            "value": "5.57kW"
        }
    ]
}